Metadata-Version: 1.0
Name: MSmas
Version: 1.4
Summary: small and compact graphick distributions
Home-page: UNKNOWN
Author: UNKNOWN
Author-email: pvana621@gmail.com
License: UNKNOWN
Platform: UNKNOWN
